LICENSE
MANIFEST.in
README.rst
setup.py
django_signedforms.egg-info/PKG-INFO
django_signedforms.egg-info/SOURCES.txt
django_signedforms.egg-info/dependency_links.txt
django_signedforms.egg-info/not-zip-safe
django_signedforms.egg-info/requires.txt
django_signedforms.egg-info/top_level.txt
signedforms/__init__.py
signedforms/forms.py
signedforms/models.py
signedforms/tests.py